{"GlobalPropertiesHash":"cR9DRi8PYoG9snCINyb9wmcP6G/Uf0qfWqXlm0U5xuk=","FingerprintPatternsHash":"gq3WsqcKBUGTSNle7RKKyXRIwh7M8ccEqOqYvIzoM04=","PropertyOverridesHash":"8ZRc1sGeVrPBx4lD717BgRaQekyh78QKV9SKsdt638U=","InputHashes":["x7FKOwtzJf8Lnf8KCgzjkfQWarby3RmBL\u002B\u002BE8YP5spI=","vQkWBVVmsPkxAytGrseuCGPI2Yma7ENiy39v4LuNF5Q=","bSgMEZmeBnZ2lMRDnHbiVxa0kY\u002B/S5Q79fkO3Ogk94c=","8dADV9AHkGwp43O\u002Bmjg8XfOuz3obCNS2YX\u002BV4svQT1Q="],"CachedAssets":{"x7FKOwtzJf8Lnf8KCgzjkfQWarby3RmBL\u002B\u002BE8YP5spI=":{"Identity":"C:\\Users\\nalag\\source\\repos\\NttDataRetoTecnicoFS\\NttDataRetoTecnicoFS\\wwwroot\\index.html","SourceId":"NttDataRetoTecnicoFS","SourceType":"Discovered","ContentRoot":"C:\\Users\\nalag\\source\\repos\\NttDataRetoTecnicoFS\\NttDataRetoTecnicoFS\\wwwroot\\","BasePath":"/","RelativePath":"index#[.{fingerprint}]?.html","AssetKind":"All","AssetMode":"All","AssetRole":"Primary","AssetMergeBehavior":null,"AssetMergeSource":"","RelatedAsset":null,"AssetTraitName":null,"AssetTraitValue":null,"Fingerprint":"e7qrn662x6","Integrity":"auwAonz2K3d/zDTBqMRlmgeYikkS\u002Bumti7sZSX43hWA=","CopyToOutputDirectory":"Never","CopyToPublishDirectory":"PreserveNewest","OriginalItemSpec":"wwwroot\\index.html","FileLength":2997,"LastWriteTime":"2026-01-19T16:15:53.9505739+00:00"},"vQkWBVVmsPkxAytGrseuCGPI2Yma7ENiy39v4LuNF5Q=":{"Identity":"C:\\Users\\nalag\\source\\repos\\NttDataRetoTecnicoFS\\NttDataRetoTecnicoFS\\wwwroot\\README.md","SourceId":"NttDataRetoTecnicoFS","SourceType":"Discovered","ContentRoot":"C:\\Users\\nalag\\source\\repos\\NttDataRetoTecnicoFS\\NttDataRetoTecnicoFS\\wwwroot\\","BasePath":"/","RelativePath":"README#[.{fingerprint}]?.md","AssetKind":"All","AssetMode":"All","AssetRole":"Primary","AssetMergeBehavior":null,"AssetMergeSource":"","RelatedAsset":null,"AssetTraitName":null,"AssetTraitValue":null,"Fingerprint":"hi0txp95cp","Integrity":"J8MUYI5Q1XDO2HAgtAcYjFElDM3Q5\u002BKEOQRJ2iTOJ\u002Bk=","CopyToOutputDirectory":"Never","CopyToPublishDirectory":"PreserveNewest","OriginalItemSpec":"wwwroot\\README.md","FileLength":1644,"LastWriteTime":"2026-01-19T16:34:38.5127916+00:00"}},"CachedCopyCandidates":{}}